exchange_config/__init__.py
exchange_config/exceptions.py
exchange_config/manager.py
exchange_config/data/binance.json
exchange_config/data/bitfinex.json
exchange_config/data/bitstamp.json
exchange_config/data/bybit.json
exchange_config/data/deribit.json
exchange_config/data/dydx.json
exchange_config/data/hitbtc.json
exchange_config/data/hyperliquid.json
exchange_config/data/kraken.json
exchange_config/data/kucoin.json
exchange_config/data/okx.json
exchange_config/exchanges/__init__.py
exchange_config/exchanges/base.py
exchange_config/exchanges/binance.py
exchange_config/exchanges/bitfinex.py
exchange_config/exchanges/bitstamp.py
exchange_config/exchanges/bybit.py
exchange_config/exchanges/deribit.py
exchange_config/exchanges/dydx.py
exchange_config/exchanges/factory.py
exchange_config/exchanges/hitbtc.py
exchange_config/exchanges/hyperliquid.py
exchange_config/exchanges/kraken.py
exchange_config/exchanges/kucoin.py
exchange_config/exchanges/okx.py
exchange_config/overrides/__init__.py
exchange_config/overrides/applicator.py
exchange_config/overrides/settings_parser.py
shared_exchange_config-0.0.16.dist-info/METADATA
shared_exchange_config-0.0.16.dist-info/WHEEL
shared_exchange_config-0.0.16.dist-info/top_level.txt
shared_exchange_config-0.0.16.dist-info/RECORD
